source/__init__.py
source/source.py
source/lib/Argument.py
source/lib/Command_function.py
source/lib/__init__.py
source/lib/help.py
Video_Audio_Image_Downloader-0.1.3.dist-info/METADATA
Video_Audio_Image_Downloader-0.1.3.dist-info/WHEEL
Video_Audio_Image_Downloader-0.1.3.dist-info/entry_points.txt
Video_Audio_Image_Downloader-0.1.3.dist-info/top_level.txt
Video_Audio_Image_Downloader-0.1.3.dist-info/RECORD
